intellivoid/__init__.py
intellivoid/exceptions.py
intellivoid/aio/__init__.py
intellivoid/aio/coa.py
intellivoid/aio/accounts/__init__.py
intellivoid/aio/accounts/user.py
intellivoid/aio/application/__init__.py
intellivoid/aio/application/settings.py
intellivoid/sync/__init__.py
intellivoid/sync/accounts/__init__.py
intellivoid/sync/accounts/user.py
intellivoid/sync/application/__init__.py
intellivoid/sync/application/exceptions.py
intellivoid/sync/application/settings.py
intellivoid/sync/coa/__init__.py
intellivoid/sync/coa/coa.py
intellivoid/sync/coa/exceptions.py
intellivoid-1.0.7.dist-info/LICENSE
intellivoid-1.0.7.dist-info/METADATA
intellivoid-1.0.7.dist-info/WHEEL
intellivoid-1.0.7.dist-info/top_level.txt
intellivoid-1.0.7.dist-info/RECORD
