Metadata-Version: 2.1
Name: intellivoid
Version: 1.0.7
Summary: Official Intellivoid Services API Wrapper for Python
Home-page: https://accounts.intellivoid.net/
Author: Intellivoid Technologies
Author-email: netkas@intellivoid.net
License: UNKNOWN
Platform: UNKNOWN
Requires-Dist: requests (>=2.3.0)
Requires-Dist: httpx
Requires-Dist: trio
